README.md
setup.py
ibm935/__init__.py
ibm935/data
ibm935/version.py
ibm935.egg-info/PKG-INFO
ibm935.egg-info/SOURCES.txt
ibm935.egg-info/dependency_links.txt
ibm935.egg-info/top_level.txt